discord_api/__init__.py
discord_api/channels.py
discord_api/client.py
discord_api/clientuser.py
discord_api/command.py
discord_api/dispatch.py
discord_api/embed.py
discord_api/errors.py
discord_api/fast.py
discord_api/gateway.py
discord_api/guild.py
discord_api/http.py
discord_api/interaction.py
discord_api/member.py
discord_api/role.py
discord_api/route.py
discord_api/user.py
discord_api/ext/commands/__init__.py
discord_api/ext/commands/bot.py
discord_api/ext/commands/cogs.py
discord_api/ext/commands/errors.py
discord_api/ext/commands/option.py
discord_api/low/__init__.py
discord_api/low/client.py
discord_api/low/gateway.py
discord_api.py-0.2.1.dist-info/LICENSE
discord_api.py-0.2.1.dist-info/METADATA
discord_api.py-0.2.1.dist-info/WHEEL
discord_api.py-0.2.1.dist-info/entry_points.txt
discord_api.py-0.2.1.dist-info/top_level.txt
discord_api.py-0.2.1.dist-info/RECORD
